[
    {
        "featureType": "all",
        "elementType": "labels.text.stroke",
        "stylers": [
            {
                "color": "#f7d79a"
            }
        ]
    },
    {
        "featureType": "administrative",
        "elementType": "labels.text.fill",
        "stylers": [
            {
                "color": "#895c2f"
            }
        ]
    },
    {
        "featureType": "landscape",
        "elementType": "geometry.fill",
        "stylers": [
            {
                "color": "#ea9d44"
            },
            {
                "saturation": "-7"
            },
            {
                "lightness": "6"
            }
        ]
    },
    {
        "featureType": "landscape.natural.landcover",
        "elementType": "geometry.fill",
        "stylers": [
            {
                "color": "#ea9d44"
            },
            {
                "visibility": "on"
            }
        ]
    },
    {
        "featureType": "landscape.natural.terrain",
        "elementType": "geometry.fill",
        "stylers": [
            {
                "color": "#ff0000"
            }
        ]
    },
    {
        "featureType": "poi.attraction",
        "elementType": "geometry.fill",
        "stylers": [
            {
                "color": "#a94835"
            }
        ]
    },
    {
        "featureType": "poi.attraction",
        "elementType": "labels.text",
        "stylers": [
            {
                "visibility": "on"
            }
        ]
    },
    {
        "featureType": "poi.attraction",
        "elementType": "labels.text.fill",
        "stylers": [
            {
                "color": "#8c5117"
            }
        ]
    },
    {
        "featureType": "poi.attraction",
        "elementType": "labels.icon",
        "stylers": [
            {
                "color": "#a3805f"
            }
        ]
    },
    {
        "featureType": "poi.business",
        "elementType": "labels.text.fill",
        "stylers": [
            {
                "color": "#d48c45"
            }
        ]
    },
    {
        "featureType": "poi.business",
        "elementType": "labels.icon",
        "stylers": [
            {
                "color": "#ba8e63"
            }
        ]
    },
    {
        "featureType": "poi.government",
        "elementType": "labels.text",
        "stylers": [
            {
                "visibility": "simplified"
            }
        ]
    },
    {
        "featureType": "poi.government",
        "elementType": "labels.icon",
        "stylers": [
            {
                "visibility": "off"
            }
        ]
    },
    {
        "featureType": "poi.medical",
        "elementType": "labels.text",
        "stylers": [
            {
                "visibility": "off"
            }
        ]
    },
    {
        "featureType": "poi.medical",
        "elementType": "labels.icon",
        "stylers": [
            {
                "visibility": "off"
            }
        ]
    },
    {
        "featureType": "poi.park",
        "elementType": "geometry.fill",
        "stylers": [
            {
                "color": "#c6d9a6"
            }
        ]
    },
    {
        "featureType": "poi.place_of_worship",
        "elementType": "labels.text",
        "stylers": [
            {
                "visibility": "off"
            }
        ]
    },
    {
        "featureType": "poi.place_of_worship",
        "elementType": "labels.icon",
        "stylers": [
            {
                "visibility": "off"
            }
        ]
    },
    {
        "featureType": "poi.school",
        "elementType": "labels.text",
        "stylers": [
            {
                "visibility": "on"
            }
        ]
    },
    {
        "featureType": "poi.sports_complex",
        "elementType": "labels.text",
        "stylers": [
            {
                "visibility": "off"
            }
        ]
    },
    {
        "featureType": "poi.sports_complex",
        "elementType": "labels.icon",
        "stylers": [
            {
                "visibility": "off"
            }
        ]
    },
    {
        "featureType": "road",
        "elementType": "geometry.fill",
        "stylers": [
            {
                "color": "#fbeedc"
            }
        ]
    },
    {
        "featureType": "road",
        "elementType": "geometry.stroke",
        "stylers": [
            {
                "visibility": "on"
            },
            {
                "color": "#ceb491"
            }
        ]
    },
    {
        "featureType": "road",
        "elementType": "labels.text.fill",
        "stylers": [
            {
                "color": "#d48c45"
            }
        ]
    },
    {
        "featureType": "water",
        "elementType": "geometry.fill",
        "stylers": [
            {
                "color": "#3c8ca2"
            },
            {
                "lightness": "13"
            }
        ]
    }
]